prometheus_xmpp/__init__.py
prometheus_xmpp/__main__.py
prometheus_xmpp_alerts-0.6.0.dist-info/licenses/LICENSE
prometheus_xmpp_alerts-0.6.0.dist-info/METADATA
prometheus_xmpp_alerts-0.6.0.dist-info/WHEEL
prometheus_xmpp_alerts-0.6.0.dist-info/entry_points.txt
prometheus_xmpp_alerts-0.6.0.dist-info/top_level.txt
prometheus_xmpp_alerts-0.6.0.dist-info/RECORD
