Metadata-Version: 2.4
Name: prometheus-xmpp-alerts
Version: 0.6.0
Summary: Prometheus XMPP Alerts hook
Author-email: Jelmer Vernooij <jelmer@jelmer.uk>
License: Apachev2
Project-URL: Homepage, https://jelmer.uk/code/prometheus-xmpp-alerts
Project-URL: Bug Tracker, https://github.com/jelmer/prometheus-xmpp-alerts/issues
Project-URL: Repository, https://github.com/jelmer/prometheus-xmpp-alerts
Project-URL: GitHub, https://github.com/jelmer/prometheus-xmpp-alerts
Keywords: prometheus xmpp jabber
Classifier: Programming Language :: Python :: 3.13
Classifier: Programming Language :: Python :: 3.12
Classifier: Programming Language :: Python :: 3.11
Classifier: Programming Language :: Python :: 3.10
Classifier: Programming Language :: Python :: 3.9
Requires-Python: >=3.9
License-File: LICENSE
Requires-Dist: slixmpp
Requires-Dist: aiohttp
Requires-Dist: pytz
Requires-Dist: pyyaml
Requires-Dist: aiohttp_openmetrics
Requires-Dist: jinja2
Requires-Dist: bs4
Provides-Extra: testing
Requires-Dist: pytz; extra == "testing"
Provides-Extra: dev
Requires-Dist: ruff==0.12.12; extra == "dev"
Dynamic: license-file
